{
  "tides": [
    {
      "time": "2025-07-20T22:03:00+00:00",
      "height_m": 0.5062758368178483,
      "type": "high"
    },
    {
      "time": "2025-07-21T04:39:00+00:00",
      "height_m": -0.5299657722993077,
      "type": "low"
    },
    {
      "time": "2025-07-21T10:54:00+00:00",
      "height_m": 0.44705016241758194,
      "type": "high"
    },
    {
      "time": "2025-07-21T17:08:00+00:00",
      "height_m": -0.44355142127719077,
      "type": "low"
    },
    {
      "time": "2025-07-21T23:13:00+00:00",
      "height_m": 0.5540846024096029,
      "type": "high"
    },
    {
      "time": "2025-07-22T05:39:00+00:00",
      "height_m": -0.597301583413412,
      "type": "low"
    },
    {
      "time": "2025-07-22T11:53:00+00:00",
      "height_m": 0.5523583216800311,
      "type": "high"
    },
    {
      "time": "2025-07-22T18:07:00+00:00",
      "height_m": -0.5375843715765248,
      "type": "low"
    },
    {
      "time": "2025-07-23T00:11:00+00:00",
      "height_m": 0.6111284034088077,
      "type": "high"
    },
    {
      "time": "2025-07-23T06:29:00+00:00",
      "height_m": -0.6565573660892574,
      "type": "low"
    },
    {
      "time": "2025-07-23T12:42:00+00:00",
      "height_m": 0.6464194922591145,
      "type": "high"
    },
    {
      "time": "2025-07-23T18:57:00+00:00",
      "height_m": -0.612530322037838,
      "type": "low"
    },
    {
      "time": "2025-07-24T01:00:00+00:00",
      "height_m": 0.6543415861132549,
      "type": "high"
    },
    {
      "time": "2025-07-24T07:12:00+00:00",
      "height_m": -0.6961919466228763,
      "type": "low"
    },
    {
      "time": "2025-07-24T07:13:00+00:00",
      "height_m": -0.6961918858654467,
      "type": "low"
    },
    {
      "time": "2025-07-24T13:25:00+00:00",
      "height_m": 0.7143542243243856,
      "type": "high"
    },
    {
      "time": "2025-07-24T19:41:00+00:00",
      "height_m": -0.6536796093605615,
      "type": "low"
    },
    {
      "time": "2025-07-25T01:42:00+00:00",
      "height_m": 0.6712374044856018,
      "type": "high"
    },
    {
      "time": "2025-07-25T07:51:00+00:00",
      "height_m": -0.7113190281069606,
      "type": "low"
    },
    {
      "time": "2025-07-25T14:04:00+00:00",
      "height_m": 0.7498369547803474,
      "type": "high"
    },
    {
      "time": "2025-07-25T20:20:00+00:00",
      "height_m": -0.6587268654573866,
      "type": "low"
    },
    {
      "time": "2025-07-26T02:20:00+00:00",
      "height_m": 0.6581438432316619,
      "type": "high"
    },
    {
      "time": "2025-07-26T08:26:00+00:00",
      "height_m": -0.7010297871099719,
      "type": "low"
    },
    {
      "time": "2025-07-26T14:40:00+00:00",
      "height_m": 0.7523562171840065,
      "type": "high"
    },
    {
      "time": "2025-07-26T20:56:00+00:00",
      "height_m": -0.6333663184681235,
      "type": "low"
    },
    {
      "time": "2025-07-27T02:55:00+00:00",
      "height_m": 0.6174658495743004,
      "type": "high"
    },
    {
      "time": "2025-07-27T08:59:00+00:00",
      "height_m": -0.6668602321018817,
      "type": "low"
    },
    {
      "time": "2025-07-27T15:14:00+00:00",
      "height_m": 0.7252561666717772,
      "type": "high"
    },
    {
      "time": "2025-07-27T21:30:00+00:00",
      "height_m": -0.5869649897588859,
      "type": "low"
    },
    {
      "time": "2025-07-28T03:28:00+00:00",
      "height_m": 0.5549541038916385,
      "type": "high"
    },
    {
      "time": "2025-07-28T09:29:00+00:00",
      "height_m": -0.6117236525709944,
      "type": "low"
    },
    {
      "time": "2025-07-28T15:46:00+00:00",
      "height_m": 0.6738802932352567,
      "type": "high"
    },
    {
      "time": "2025-07-28T22:03:00+00:00",
      "height_m": -0.5285961662620466,
      "type": "low"
    },
    {
      "time": "2025-07-28T22:50:00+00:00",
      "height_m": -1.223980365070746,
      "type": "low"
    },
    {
      "time": "2025-07-29T04:01:00+00:00",
      "height_m": 0.477349319278143,
      "type": "high"
    },
    {
      "time": "2025-07-29T05:03:00+00:00",
      "height_m": 0.9383409970976787,
      "type": "high"
    },
    {
      "time": "2025-07-29T09:58:00+00:00",
      "height_m": -0.5390622601796072,
      "type": "low"
    },
    {
      "time": "2025-07-29T10:53:00+00:00",
      "height_m": -1.0785521632815516,
      "type": "low"
    },
    {
      "time": "2025-07-29T16:17:00+00:00",
      "height_m": 0.6038667419439249,
      "type": "high"
    },
    {
      "time": "2025-07-29T17:16:00+00:00",
      "height_m": 1.0971736808139363,
      "type": "high"
    },
    {
      "time": "2025-07-29T22:35:00+00:00",
      "height_m": -0.4644120730749535,
      "type": "low"
    },
    {
      "time": "2025-07-29T23:25:00+00:00",
      "height_m": -1.0878923298245944,
      "type": "low"
    },
    {
      "time": "2025-07-30T04:35:00+00:00",
      "height_m": 0.39090605777902876,
      "type": "high"
    },
    {
      "time": "2025-07-30T05:39:00+00:00",
      "height_m": 0.82123545981248,
      "type": "high"
    },
    {
      "time": "2025-07-30T10:29:00+00:00",
      "height_m": -0.45243788753782604,
      "type": "low"
    },
    {
      "time": "2025-07-30T11:30:00+00:00",
      "height_m": -0.945090850913876,
      "type": "low"
    },
    {
      "time": "2025-07-30T16:49:00+00:00",
      "height_m": 0.5200928749766498,
      "type": "high"
    },
    {
      "time": "2025-07-30T17:52:00+00:00",
      "height_m": 0.9138131430356211,
      "type": "high"
    },
    {
      "time": "2025-07-30T23:11:00+00:00",
      "height_m": -0.3972895826245246,
      "type": "low"
    },
    {
      "time": "2025-07-31T00:01:00+00:00",
      "height_m": -0.9386789498050369,
      "type": "low"
    },
    {
      "time": "2025-07-31T05:12:00+00:00",
      "height_m": 0.3013158753902157,
      "type": "high"
    },
    {
      "time": "2025-07-31T06:17:00+00:00",
      "height_m": 0.6965607708434823,
      "type": "high"
    },
    {
      "time": "2025-07-31T11:03:00+00:00",
      "height_m": -0.3559289192448049,
      "type": "low"
    },
    {
      "time": "2025-07-31T12:11:00+00:00",
      "height_m": -0.7920506125301953,
      "type": "low"
    },
    {
      "time": "2025-07-31T17:24:00+00:00",
      "height_m": 0.42697613091262093,
      "type": "high"
    },
    {
      "time": "2025-07-31T18:32:00+00:00",
      "height_m": 0.7248211094363861,
      "type": "high"
    },
    {
      "time": "2025-07-31T23:53:00+00:00",
      "height_m": -0.32922491007895743,
      "type": "low"
    },
    {
      "time": "2025-08-01T00:43:00+00:00",
      "height_m": -0.7846468630109864,
      "type": "low"
    },
    {
      "time": "2025-08-01T06:00:00+00:00",
      "height_m": 0.2159009779746974,
      "type": "high"
    },
    {
      "time": "2025-08-01T07:02:00+00:00",
      "height_m": 0.5753604858223639,
      "type": "high"
    },
    {
      "time": "2025-08-01T11:46:00+00:00",
      "height_m": -0.25589577019923254,
      "type": "low"
    },
    {
      "time": "2025-08-01T13:01:00+00:00",
      "height_m": -0.6361954795909667,
      "type": "low"
    },
    {
      "time": "2025-08-01T18:09:00+00:00",
      "height_m": 0.33118417216715956,
      "type": "high"
    },
    {
      "time": "2025-08-01T19:20:00+00:00",
      "height_m": 0.5457457533143699,
      "type": "high"
    },
    {
      "time": "2025-08-02T00:52:00+00:00",
      "height_m": -0.26740078081425095,
      "type": "low"
    },
    {
      "time": "2025-08-02T01:36:00+00:00",
      "height_m": -0.6408801236083673,
      "type": "low"
    },
    {
      "time": "2025-08-02T07:59:00+00:00",
      "height_m": 0.47879481956036,
      "type": "high"
    },
    {
      "time": "2025-08-02T14:08:00+00:00",
      "height_m": -0.5095622968963689,
      "type": "low"
    },
    {
      "time": "2025-08-02T20:26:00+00:00",
      "height_m": 0.40586722053319674,
      "type": "high"
    },
    {
      "time": "2025-08-03T02:45:00+00:00",
      "height_m": -0.539093847829014,
      "type": "low"
    },
    {
      "time": "2025-08-03T09:14:00+00:00",
      "height_m": 0.4462650170255983,
      "type": "high"
    },
    {
      "time": "2025-08-03T15:35:00+00:00",
      "height_m": -0.46860052686497156,
      "type": "low"
    },
    {
      "time": "2025-08-03T21:51:00+00:00",
      "height_m": 0.3571715600760892,
      "type": "high"
    }
  ]
}